nccsv/__init__.py
nccsv/__main__.py
nccsv/csvutil.py
nccsv/entry.py
nccsv/grid.py
nccsv-0.2.dist-info/LICENSE
nccsv-0.2.dist-info/METADATA
nccsv-0.2.dist-info/WHEEL
nccsv-0.2.dist-info/entry_points.txt
nccsv-0.2.dist-info/top_level.txt
nccsv-0.2.dist-info/RECORD
