Metadata-Version: 2.1
Name: nccsv
Version: 0.2
Summary: Ncurses CSV Editor written in Python
Home-page: https://github.com/ssebs/nccsv
Author: Sebastian Safari
Author-email: contact@ssebs.com
License: MIT
Platform: UNKNOWN
Classifier: License :: OSI Approved :: MIT License
Classifier: Programming Language :: Python
Classifier: Programming Language :: Python :: 3
Classifier: Programming Language :: Python :: 3.6
Classifier: Operating System :: OS Independent
Requires-Python: >=3.6.0
